Financiers/__init__.py
Financiers/quotes.py
Financiers/stock.py
Brainrot_Stocks-0.1.7.dist-info/LICENSE
Brainrot_Stocks-0.1.7.dist-info/METADATA
Brainrot_Stocks-0.1.7.dist-info/WHEEL
Brainrot_Stocks-0.1.7.dist-info/entry_points.txt
Brainrot_Stocks-0.1.7.dist-info/top_level.txt
Brainrot_Stocks-0.1.7.dist-info/RECORD
