Metadata-Version: 2.1
Name: Brainrot-Stocks
Version: 0.1.7
Summary: Get stock data with unwanted brainrot in your Python app.
Author-email: Reyhan Abdul Quayum <rrq2003@nyu.edu>, Rashed Alneyadi <raa9917@nyu.edu>, Sia Chen <mc9114@nyu.edu>, Yu Zhang <yz7669@nyu.edu>, Chloe Han <jh7316@nyu.edu>
License: GNU GENERAL PUBLIC LICENSE
Project-URL: Homepage, https://github.com/software-students-fall2024/3-python-package-financeeers
Project-URL: Repository, https://github.com/software-students-fall2024/3-python-package-financeeers.git
Project-URL: Bug Tracker, https://github.com/software-students-fall2024/3-python-package-financeeers/issues
Keywords: python,package,finance,stocks,API
Classifier: Programming Language :: Python :: 3
Classifier: Intended Audience :: Developers
Classifier: Topic :: Software Development :: Libraries :: Python Modules
Classifier: License :: OSI Approved :: GNU General Public License v3 (GPLv3)
Classifier: Operating System :: OS Independent
Requires-Python: >=3.7
License-File: LICENSE
Requires-Dist: pandas
Requires-Dist: requests
Requires-Dist: python-dotenv
Requires-Dist: numpy
Requires-Dist: matplotlib
Requires-Dist: datetime
Provides-Extra: dev
Requires-Dist: pytest; extra == "dev"
